setup.cfg
setup.py
neurio/__init__.py
neurio.egg-info/PKG-INFO
neurio.egg-info/SOURCES.txt
neurio.egg-info/dependency_links.txt
neurio.egg-info/requires.txt
neurio.egg-info/top_level.txt