Metadata-Version: 1.1
Name: neurio
Version: 0.2.9
Summary: Neurio energy sensor and appliance automation API library
Home-page: https://github.com/jordanh/neurio-python
Author: Jordan Husney
Author-email: jordan.husney@gmail.com
License: UNKNOWN
Download-URL: https://github.com/jordanh/neurio-python/tarball/0.2.9
Keywords: neurio,iot,energy,sensor,smarthome,automation
Platform: UNKNOWN
